elecnova_client/__init__.py
elecnova_client/auth.py
elecnova_client/client.py
elecnova_client/client_sync.py
elecnova_client/exceptions.py
elecnova_client/models.py
elecnova_client-0.2.2.dist-info/METADATA
elecnova_client-0.2.2.dist-info/WHEEL
elecnova_client-0.2.2.dist-info/RECORD
