Metadata-Version: 2.4
Name: elecnova-client
Version: 0.2.2
Summary: Python client for Elecnova ECO EMS Cloud API
Author-email: Steen Elektriciteit <info@steenelektriciteit.be>
License: LGPL-3.0-or-later
Requires-Python: >=3.11
Requires-Dist: httpx>=0.27.0
Requires-Dist: pydantic>=2.0.0
Provides-Extra: dev
Requires-Dist: mypy>=1.10.0; extra == 'dev'
Requires-Dist: pre-commit>=3.7.0; extra == 'dev'
Requires-Dist: pytest-asyncio>=0.23.0; extra == 'dev'
Requires-Dist: pytest-cov>=5.0.0; extra == 'dev'
Requires-Dist: pytest-httpx>=0.30.0; extra == 'dev'
Requires-Dist: pytest>=8.0.0; extra == 'dev'
Requires-Dist: ruff>=0.4.0; extra == 'dev'
